README.rst
setup.py
telecast/__init__.py
telecast/client.py
telecast/codes.py
telecast/exceptions.py
telecast/marshalling.py
telecast/test.py
telecast.egg-info/PKG-INFO
telecast.egg-info/SOURCES.txt
telecast.egg-info/dependency_links.txt
telecast.egg-info/requires.txt
telecast.egg-info/top_level.txt
telecast/contrib/__init__.py
telecast/contrib/django/__init__.py
telecast/contrib/django/client.py
telecast/contrib/rest_framework/__init__.py
telecast/contrib/rest_framework/server.py