Metadata-Version: 1.1
Name: telecast
Version: 0.5.3
Summary: Portable REST/JSON RPC implementation.
Home-page: https://github.com/and3rson/telecast
Author: Andrew Dunai
Author-email: a@dun.ai
License: UNKNOWN
Keywords: python json rest rpc
Platform: UNKNOWN
Classifier: Development Status :: 4 - Beta
Classifier: Intended Audience :: Developers
Classifier: Programming Language :: Python :: 3.6
